tasker/__init__.py
tasker_tasks_cli-0.0.6.data/scripts/tasker
tasker_tasks_cli-0.0.6.data/scripts/tasker.py
tasker_tasks_cli-0.0.6.dist-info/licenses/LICENSE.md
tasker_tasks_cli-0.0.6.dist-info/METADATA
tasker_tasks_cli-0.0.6.dist-info/WHEEL
tasker_tasks_cli-0.0.6.dist-info/top_level.txt
tasker_tasks_cli-0.0.6.dist-info/RECORD
