Metadata-Version: 2.4
Name: tasker-tasks-cli
Version: 0.0.6
Summary: tasker: cli based task manager.
Home-page: https://github.com/monotone-the-musical/tasker
Author: mtm
Author-email: MTM <monotone.the.musical@gmail.com>
Project-URL: Homepage, https://github.com/monotone-the-musical/tasker
Project-URL: Bug Tracker, https://github.com/monotone-the-musical/tasker/issues
Classifier: Programming Language :: Python :: 3
Classifier: License :: OSI Approved :: MIT License
Classifier: Operating System :: POSIX :: Linux
License-File: LICENSE.md
Requires-Dist: configparser
Requires-Dist: iterfzf
Requires-Dist: python-dateutil
Dynamic: author
Dynamic: home-page
Dynamic: license-file
